vlmrun/constants.py
vlmrun/version.py
vlmrun/cli/__init__.py
vlmrun/cli/cli.py
vlmrun/cli/_cli/__init__.py
vlmrun/cli/_cli/config.py
vlmrun/cli/_cli/datasets.py
vlmrun/cli/_cli/files.py
vlmrun/cli/_cli/fine_tuning.py
vlmrun/cli/_cli/generate.py
vlmrun/cli/_cli/hub.py
vlmrun/cli/_cli/models.py
vlmrun/cli/_cli/predictions.py
vlmrun/client/__init__.py
vlmrun/client/agent.py
vlmrun/client/artifacts.py
vlmrun/client/base_requestor.py
vlmrun/client/client.py
vlmrun/client/datasets.py
vlmrun/client/exceptions.py
vlmrun/client/executions.py
vlmrun/client/feedback.py
vlmrun/client/files.py
vlmrun/client/fine_tuning.py
vlmrun/client/hub.py
vlmrun/client/models.py
vlmrun/client/predictions.py
vlmrun/client/types.py
vlmrun/common/image.py
vlmrun/common/pdf.py
vlmrun/common/pydantic.py
vlmrun/common/utils.py
vlmrun/common/video.py
vlmrun/common/viz.py
vlmrun/common/webhook.py
vlmrun/types/__init__.py
vlmrun/types/abstract.py
vlmrun/types/refs.py
vlmrun-0.4.0.dist-info/licenses/LICENSE
vlmrun-0.4.0.dist-info/METADATA
vlmrun-0.4.0.dist-info/WHEEL
vlmrun-0.4.0.dist-info/entry_points.txt
vlmrun-0.4.0.dist-info/top_level.txt
vlmrun-0.4.0.dist-info/RECORD
