Metadata-Version: 2.4
Name: vlmrun
Version: 0.4.0
Summary: Official Python SDK for VLM Run
Author-email: VLM Support <support@vlm.com>
License: Apache-2.0
Classifier: Development Status :: 4 - Beta
Classifier: Programming Language :: Python
Classifier: Environment :: Console
Classifier: Intended Audience :: Developers
Classifier: Intended Audience :: Education
Classifier: Intended Audience :: Information Technology
Classifier: Intended Audience :: Science/Research
Classifier: Topic :: Software Development :: Libraries
Classifier: Topic :: Scientific/Engineering :: Artificial Intelligence
Classifier: Topic :: Scientific/Engineering :: Image Processing
Classifier: License :: OSI Approved :: Apache Software License
Classifier: Operating System :: POSIX :: Linux
Classifier: Operating System :: MacOS
Classifier: Programming Language :: Python :: 3 :: Only
Classifier: Programming Language :: Python :: 3.10
Classifier: Programming Language :: Python :: 3.11
Requires-Python: >=3.9
License-File: LICENSE
Requires-Dist: cachetools
Requires-Dist: IPython
Requires-Dist: loguru
Requires-Dist: opencv-python>=4.8.0
Requires-Dist: pandas
Requires-Dist: Pillow>=10.2.0
Requires-Dist: pydantic<3,>=2.5
Requires-Dist: pydantic_core>=2.23.4
Requires-Dist: requests
Requires-Dist: rich
Requires-Dist: tabulate
Requires-Dist: tenacity
Requires-Dist: tqdm
Requires-Dist: typer>=0.9.0
Requires-Dist: vlmrun-hub>=0.1.28
Provides-Extra: test
Requires-Dist: pytest; extra == "test"
Requires-Dist: openai; extra == "test"
Requires-Dist: pre-commit; extra == "test"
Provides-Extra: build
Requires-Dist: twine; extra == "build"
Requires-Dist: build; extra == "build"
Provides-Extra: openai
Requires-Dist: openai>=1.0.0; extra == "openai"
Provides-Extra: video
Requires-Dist: numpy>=1.24.0; extra == "video"
Provides-Extra: doc
Requires-Dist: pypdfium2>=4.30.0; extra == "doc"
Provides-Extra: all
Requires-Dist: numpy>=1.24.0; extra == "all"
Requires-Dist: pypdfium2>=4.30.0; extra == "all"
Requires-Dist: openai>=1.0.0; extra == "all"
Dynamic: license-file
